pytamaro_extra/__init__.py
pytamaro_extra/de/__init__.py
pytamaro_extra/de/primitives.py
pytamaro_extra/graphic.py
pytamaro_extra/it/__init__.py
pytamaro_extra/it/primitives.py
pytamaro_extra/primitives.py
pytamaro_extra-0.1.0.dist-info/WHEEL
pytamaro_extra-0.1.0.dist-info/METADATA
pytamaro_extra-0.1.0.dist-info/RECORD
