Metadata-Version: 2.1
Name: pytamaro-extra
Version: 0.1.0
Summary: Extra functionalities for PyTamaro
Author: Luca Chiodini
Author-email: luca@chiodini.org
Requires-Python: >=3.7,<4.0
Classifier: Programming Language :: Python :: 3
Classifier: Programming Language :: Python :: 3.10
Classifier: Programming Language :: Python :: 3.7
Classifier: Programming Language :: Python :: 3.8
Classifier: Programming Language :: Python :: 3.9
Requires-Dist: pytamaro (>=0.1.1,<0.2.0)
Requires-Dist: skia-python (>=87.4,<88.0)
